{"nm":"Are you ready","ddd":0,"h":1080,"w":1920,"meta":{"g":"@lottiefiles/toolkit-js 0.26.1"},"layers":[{"ty":4,"nm":"line","sr":1,"st":0,"op":121,"ip":0,"hd":false,"ddd":0,"bm":0,"hasMask":false,"ao":0,"ks":{"a":{"a":0,"k":[24.267,-186.05,0],"ix":1},"s":{"a":1,"k":[{"o":{"x":0.167,"y":0.167},"i":{"x":0.833,"y":0.833},"s":[30.75,30.75,100],"t":0},{"s":[98.898,98.898,100],"t":24}],"ix":6},"sk":{"a":0,"k":0},"p":{"a":1,"k":[{"o":{"x":0.333,"y":0.333},"i":{"x":0,"y":0},"s":[964.132,350,0],"t":0,"ti":[0,0,0],"to":[0,0,0]},{"o":{"x":0.333,"y":0},"i":{"x":0.125,"y":0.95},"s":[964.132,350,0],"t":24,"ti":[0,-58.968,0],"to":[0,58.968,0]},{"o":{"x":0.333,"y":0.333},"i":{"x":0.125,"y":0.125},"s":[964.132,703.81,0],"t":60,"ti":[0,0,0],"to":[0,0,0]},{"o":{"x":0.333,"y":0},"i":{"x":0,"y":0.962},"s":[964.132,703.81,0],"t":96,"ti":[0,58.968,0],"to":[0,-58.968,0]},{"s":[964.132,350,0],"t":120}],"ix":2},"r":{"a":0,"k":0,"ix":10},"sa":{"a":0,"k":0},"o":{"a":0,"k":100,"ix":11}},"ef":[],"shapes":[{"ty":"gr","bm":0,"hd":false,"mn":"ADBE Vector Group","nm":"形状 1","ix":1,"cix":2,"np":3,"it":[{"ty":"sh","bm":0,"hd":false,"mn":"ADBE Vector Shape - Group","nm":"路径 1","ix":1,"d":1,"ks":{"a":0,"k":{"c":false,"i":[[0,0],[0,0]],"o":[[0,0],[0,0]],"v":[[-774,-188],[810,-188]]},"ix":2}},{"ty":"st","bm":0,"hd":false,"mn":"ADBE Vector Graphic - Stroke","nm":"描边 1","lc":1,"lj":1,"ml":4,"o":{"a":0,"k":100,"ix":4},"w":{"a":0,"k":9,"ix":5},"c":{"a":0,"k":[0,0,0],"ix":3}},{"ty":"tr","a":{"a":0,"k":[0,0],"ix":1},"s":{"a":0,"k":[100,100],"ix":3},"sk":{"a":0,"k":0,"ix":4},"p":{"a":0,"k":[0,0],"ix":2},"r":{"a":0,"k":0,"ix":6},"sa":{"a":0,"k":0,"ix":5},"o":{"a":0,"k":100,"ix":7}}]}],"ind":1},{"ty":4,"nm":"Mask","sr":1,"st":0,"op":121,"ip":0,"hd":false,"ddd":0,"bm":0,"hasMask":false,"td":1,"ao":0,"ks":{"a":{"a":0,"k":[0,0,0],"ix":1},"s":{"a":0,"k":[100.372,101.114,100],"ix":6},"sk":{"a":0,"k":0},"p":{"a":0,"k":[22.74,3.44,0],"ix":2},"r":{"a":0,"k":0,"ix":10},"sa":{"a":0,"k":0},"o":{"a":0,"k":100,"ix":11}},"ef":[],"shapes":[{"ty":"gr","bm":0,"hd":false,"mn":"ADBE Vector Group","nm":"矩形 1","ix":1,"cix":2,"np":3,"it":[{"ty":"rc","bm":0,"hd":false,"mn":"ADBE Vector Shape - Rect","nm":"矩形路径 1","d":1,"p":{"a":0,"k":[0,0],"ix":3},"r":{"a":0,"k":0,"ix":4},"s":{"a":0,"k":[1586.555,394.547],"ix":2}},{"ty":"fl","bm":0,"hd":false,"mn":"ADBE Vector Graphic - Fill","nm":"填充 1","c":{"a":0,"k":[0,0.5922,0.9255],"ix":4},"r":1,"o":{"a":0,"k":100,"ix":5}},{"ty":"tr","a":{"a":0,"k":[0,0],"ix":1},"s":{"a":0,"k":[100,100],"ix":3},"sk":{"a":0,"k":0,"ix":4},"p":{"a":0,"k":[-4.723,-382.727],"ix":2},"r":{"a":0,"k":0,"ix":6},"sa":{"a":0,"k":0,"ix":5},"o":{"a":0,"k":100,"ix":7}}]}],"ind":2,"parent":1},{"ty":5,"nm":"READY ","sr":1,"st":0,"op":121,"ip":0,"hd":false,"ddd":0,"bm":0,"tt":1,"hasMask":false,"ao":0,"ks":{"a":{"a":0,"k":[0,0,0],"ix":1},"s":{"a":0,"k":[130,130,100],"ix":6},"sk":{"a":0,"k":0},"p":{"a":0,"k":[966.916,652.5,0],"ix":2},"r":{"a":0,"k":0,"ix":10},"sa":{"a":0,"k":0},"o":{"a":0,"k":100,"ix":11}},"ef":[],"t":{"m":{"a":{"a":0,"k":[0,0],"ix":2},"g":1},"p":{},"a":[],"d":{"k":[{"s":{"f":"Krungthep","s":300,"t":"READY","fc":[1,1,1],"lh":360,"tr":50,"j":2,"ca":0},"t":0}]}},"ind":3},{"ty":4,"nm":"line 2","sr":1,"st":0,"op":192,"ip":120,"hd":false,"ddd":0,"bm":0,"hasMask":false,"ao":0,"ks":{"a":{"a":0,"k":[24.267,-186.05,0],"ix":1},"s":{"a":1,"k":[{"o":{"x":0.167,"y":0.167},"i":{"x":0.833,"y":0.833},"s":[30.75,30.75,100],"t":0},{"s":[98.898,98.898,100],"t":24}],"ix":6},"sk":{"a":0,"k":0},"p":{"a":1,"k":[{"o":{"x":0.333,"y":0},"i":{"x":0,"y":0.975},"s":[964.132,350,0],"t":120,"ti":[0,-58.968,0],"to":[0,58.968,0]},{"s":[964.132,703.81,0],"t":157}],"ix":2},"r":{"a":0,"k":0,"ix":10},"sa":{"a":0,"k":0},"o":{"a":0,"k":100,"ix":11}},"ef":[],"shapes":[{"ty":"gr","bm":0,"hd":false,"mn":"ADBE Vector Group","nm":"形状 1","ix":1,"cix":2,"np":3,"it":[{"ty":"sh","bm":0,"hd":false,"mn":"ADBE Vector Shape - Group","nm":"路径 1","ix":1,"d":1,"ks":{"a":0,"k":{"c":false,"i":[[0,0],[0,0]],"o":[[0,0],[0,0]],"v":[[-774,-188],[810,-188]]},"ix":2}},{"ty":"st","bm":0,"hd":false,"mn":"ADBE Vector Graphic - Stroke","nm":"描边 1","lc":1,"lj":1,"ml":4,"o":{"a":0,"k":100,"ix":4},"w":{"a":0,"k":9,"ix":5},"c":{"a":0,"k":[0,0,0],"ix":3}},{"ty":"tr","a":{"a":0,"k":[0,0],"ix":1},"s":{"a":0,"k":[100,100],"ix":3},"sk":{"a":0,"k":0,"ix":4},"p":{"a":0,"k":[0,0],"ix":2},"r":{"a":0,"k":0,"ix":6},"sa":{"a":0,"k":0,"ix":5},"o":{"a":0,"k":100,"ix":7}}]}],"ind":4},{"ty":4,"nm":"Mask 2","sr":1,"st":0,"op":192,"ip":120,"hd":false,"ddd":0,"bm":0,"hasMask":false,"td":1,"ao":0,"ks":{"a":{"a":0,"k":[0,0,0],"ix":1},"s":{"a":0,"k":[100.372,101.114,100],"ix":6},"sk":{"a":0,"k":0},"p":{"a":0,"k":[22.74,3.44,0],"ix":2},"r":{"a":0,"k":0,"ix":10},"sa":{"a":0,"k":0},"o":{"a":0,"k":100,"ix":11}},"ef":[],"shapes":[{"ty":"gr","bm":0,"hd":false,"mn":"ADBE Vector Group","nm":"矩形 1","ix":1,"cix":2,"np":3,"it":[{"ty":"rc","bm":0,"hd":false,"mn":"ADBE Vector Shape - Rect","nm":"矩形路径 1","d":1,"p":{"a":0,"k":[0,0],"ix":3},"r":{"a":0,"k":0,"ix":4},"s":{"a":0,"k":[1586.555,394.547],"ix":2}},{"ty":"fl","bm":0,"hd":false,"mn":"ADBE Vector Graphic - Fill","nm":"填充 1","c":{"a":0,"k":[0,0.5922,0.9255],"ix":4},"r":1,"o":{"a":0,"k":100,"ix":5}},{"ty":"tr","a":{"a":0,"k":[0,0],"ix":1},"s":{"a":0,"k":[100,100],"ix":3},"sk":{"a":0,"k":0,"ix":4},"p":{"a":0,"k":[-4.723,-382.727],"ix":2},"r":{"a":0,"k":0,"ix":6},"sa":{"a":0,"k":0,"ix":5},"o":{"a":0,"k":100,"ix":7}}]}],"ind":5,"parent":4},{"ty":5,"nm":"START","sr":1,"st":96,"op":192,"ip":120,"hd":false,"ddd":0,"bm":0,"tt":1,"hasMask":false,"ao":0,"ks":{"a":{"a":0,"k":[0,0,0],"ix":1},"s":{"a":0,"k":[130,130,100],"ix":6},"sk":{"a":0,"k":0},"p":{"a":0,"k":[952.642,652.5,0],"ix":2},"r":{"a":0,"k":0,"ix":10},"sa":{"a":0,"k":0},"o":{"a":0,"k":100,"ix":11}},"ef":[],"t":{"m":{"a":{"a":0,"k":[0,0],"ix":2},"g":1},"p":{},"a":[],"d":{"k":[{"s":{"f":"Krungthep","s":300,"t":"START","fc":[1,1,1],"lh":360,"tr":50,"j":2,"ca":0},"t":0}]}},"ind":6}],"v":"5.6.10","fr":24,"op":192,"ip":0,"fonts":{"list":[{"ascent":79.0488770231605,"fClass":"","fFamily":"Krungthep","fStyle":"Regular","fName":"Krungthep","fPath":"","fWeight":"","origin":0}]},"assets":[]}